rain_ai/cache/create.py
rain_ai/cache/factory.py
rain_ai/cache/operation.py
rain_ai/core/graph/default.py
rain_ai/core/graph/graph.py
rain_ai/core/graph/visualize.py
rain_ai/core/memory/memory.py
rain_ai/core/memory/messages.py
rain_ai/core/model_load/chat_model_load.py
rain_ai/core/model_load/embedding_model_load.py
rain_ai/core/monitor/abstract.py
rain_ai/core/parser/output.py
rain_ai/core/prompt/templates.py
rain_ai/core/serialize/archive_loader.py
rain_ai/core/serialize/cloudpickle_serialize.py
rain_ai/core/serialize/schemas.py
rain_ai/core/serialize/zip_serialize.py
rain_ai/core/tool/base_class.py
rain_ai/core/tool/decorator.py
rain_ai/core/tool/schemas.py
rain_ai/core/tool/tool_load.py
rain_ai/core/tool/utils.py
rain_ai/mcp/client.py
rain_ai/mcp/server.py
rain_ai/rag/loader/custom_loader.py
rain_ai/rag/loader/document_loader.py
rain_ai/rag/loader/load_content.py
rain_ai/rag/splitter/document_splitter.py
rain_ai/rag/splitter/split_content.py
rain_ai/rag/vectorstore/operation.py
rain_ai/rag/vectorstore/vectorstore.py
rain_ai-0.1.21.dist-info/licenses/LICENSE
rain_ai-0.1.21.dist-info/METADATA
rain_ai-0.1.21.dist-info/WHEEL
rain_ai-0.1.21.dist-info/top_level.txt
rain_ai-0.1.21.dist-info/RECORD
