Metadata-Version: 2.4
Name: rain-ai
Version: 0.1.21
Summary: Ai SDK Fore Rain
Author-email: jellyrain <guodongyu6@gmail.com>
Requires-Python: >=3.12
License-File: LICENSE
Requires-Dist: aiosqlite>=0.21.0
Requires-Dist: beautifulsoup4>=4.13.4
Requires-Dist: cachetools>=5.5.2
Requires-Dist: cloudpickle>=3.1.1
Requires-Dist: httpx>=0.28.1
Requires-Dist: jq>=1.9.1
Requires-Dist: langchain>=0.3.25
Requires-Dist: langchain-chroma>=0.2.4
Requires-Dist: langchain-community>=0.3.25
Requires-Dist: langchain-mcp-adapters>=0.1.7
Requires-Dist: langchain-openai>=0.3.19
Requires-Dist: langchain-text-splitters>=0.3.8
Requires-Dist: langgraph>=0.4.8
Requires-Dist: langgraph-checkpoint-sqlite>=2.0.10
Requires-Dist: openpyxl>=3.1.5
Requires-Dist: pymupdf>=1.26.1
Requires-Dist: python-docx>=1.2.0
Dynamic: license-file
